rainfall/__init__.py
rainfall/cli.py
rainfall/config.py
rainfall/core.py
rainfall/llm.py
rainfall/parser.py
rainfall_cli-0.2.0.dist-info/METADATA
rainfall_cli-0.2.0.dist-info/WHEEL
rainfall_cli-0.2.0.dist-info/entry_points.txt
rainfall_cli-0.2.0.dist-info/licenses/LICENSE
rainfall_cli-0.2.0.dist-info/RECORD
