Metadata-Version: 2.4
Name: rainfall-cli
Version: 0.2.0
Summary: Call functions that don't exist. Let AI figure it out.
Project-URL: Homepage, https://github.com/system1970/rainfall
Project-URL: Repository, https://github.com/system1970/rainfall
Project-URL: Documentation, https://github.com/system1970/rainfall#readme
Author: system1970
License-Expression: MIT
License-File: LICENSE
Keywords: ai,function,gemini,llm,prototyping,python,stub
Classifier: Development Status :: 3 - Alpha
Classifier: Intended Audience :: Developers
Classifier: License :: OSI Approved :: MIT License
Classifier: Programming Language :: Python :: 3.10
Classifier: Programming Language :: Python :: 3.11
Classifier: Programming Language :: Python :: 3.12
Classifier: Topic :: Scientific/Engineering :: Artificial Intelligence
Classifier: Topic :: Software Development :: Libraries :: Python Modules
Requires-Python: >=3.10
Requires-Dist: click>=8.0.0
Requires-Dist: google-generativeai>=0.8.0
Requires-Dist: pillow>=10.0.0
Requires-Dist: requests>=2.28.0
Provides-Extra: dev
Requires-Dist: build>=1.0.0; extra == 'dev'
Requires-Dist: pytest>=7.0.0; extra == 'dev'
Requires-Dist: ruff>=0.1.0; extra == 'dev'
Requires-Dist: twine>=4.0.0; extra == 'dev'
